config_joker/__init__.py
config_joker/config.py
config_joker/sources/__init__.py
config_joker/sources/environment.py
config_joker/sources/jsonfile.py
config_joker/sources/source.py
config_joker/sources/yamlfile.py
config_joker/utils/__init__.py
config_joker/utils/parser.py
config_joker-0.7.0.dist-info/LICENSE
config_joker-0.7.0.dist-info/METADATA
config_joker-0.7.0.dist-info/WHEEL
config_joker-0.7.0.dist-info/RECORD
