Metadata-Version: 2.1
Name: config-joker
Version: 0.7.0
Summary: A package to ease usage of different configuration conditions in your projects.
Author: Joao Pedro Mendes Goulart
Requires-Python: >=3.7,<4.0
Classifier: Programming Language :: Python :: 3
Classifier: Programming Language :: Python :: 3.7
Classifier: Programming Language :: Python :: 3.8
Classifier: Programming Language :: Python :: 3.9
Classifier: Programming Language :: Python :: 3.10
Classifier: Programming Language :: Python :: 3.11
Requires-Dist: PyYAML (>=5.1,<6.0)
Requires-Dist: regex (>=2023.3.23,<2024.0.0)
